{
  "kind": "collectionType",
  "collectionName": "posts",
  "info": {
    "singularName": "post",
    "pluralName": "posts",
    "displayName": "post",
    "description": ""
  },
  "options": {
    "draftAndPublish": true
  },
  "pluginOptions": {},
  "attributes": {
    "title": {
      "type": "string"
    },
    "author": {
      "type": "string"
    },
    "viewsCount": {
      "type": "integer"
    },
    "rank": {
      "type": "integer"
    },
    "body": {
      "type": "richtext"
    },
    "articleHero": {
      "type": "string"
    },
    "avatar": {
      "type": "string"
    }
  }
}
